language_statistics/__init__.py
language_statistics/colorbar.py
language_statistics/language_bytes.py
language_statistics/output.svg
language_statistics/statistics.py
language_statistics/__pycache__/__init__.cpython-39.pyc
language_statistics/__pycache__/colorbar.cpython-39.pyc
language_statistics/__pycache__/language_bytes.cpython-39.pyc
language_statistics/__pycache__/statistics.cpython-39.pyc
language_statistics/data/languages.yml
langstats-1.0.4.dist-info/LICENSE.md
langstats-1.0.4.dist-info/METADATA
langstats-1.0.4.dist-info/WHEEL
langstats-1.0.4.dist-info/entry_points.txt
langstats-1.0.4.dist-info/top_level.txt
langstats-1.0.4.dist-info/RECORD
