Metadata-Version: 2.1
Name: langstats
Version: 1.0.4
Summary: Detailed visualization of programming language use in your local directories
Home-page: https://github.com/Destaq/langstats
Author: Simon Ilincev
Author-email: Simon Ilincev <simon@simonilincev.com>
Project-URL: Homepage, https://github.com/Destaq/langstats
Project-URL: Bug Tracker, https://github.com/Destaq/langstats/issues
Keywords: statistics,linguist,analysis
Classifier: Programming Language :: Python :: 3
Classifier: License :: OSI Approved :: MIT License
Classifier: Operating System :: OS Independent
Requires-Python: >=3.7
License-File: LICENSE.md
Requires-Dist: Pillow
Requires-Dist: PyYAML
Requires-Dist: pycairo
